auto_intern/__init__.py
auto_intern/__main__.py
auto_intern/chatgpt.py
auto_intern/main.py
auto_intern/report.py
auto_intern/resume.py
auto_intern-0.1.0.dist-info/LICENSE
auto_intern-0.1.0.dist-info/METADATA
auto_intern-0.1.0.dist-info/WHEEL
auto_intern-0.1.0.dist-info/entry_points.txt
auto_intern-0.1.0.dist-info/top_level.txt
auto_intern-0.1.0.dist-info/RECORD
